COPYING
LICENSE
MANIFEST.in
README.rst
default.json
default.txt
multihost.cfg
multihost.txt
setup.py
tests.py
tunir
tunir.8
vgt.json
vgt.txt
docs/Makefile
docs/aws.rst
docs/conf.py
docs/index.rst
docs/installation.rst
docs/usage.rst
docs/vagrant.rst
docs/why.rst
tunir.egg-info/PKG-INFO
tunir.egg-info/SOURCES.txt
tunir.egg-info/dependency_links.txt
tunir.egg-info/entry_points.txt
tunir.egg-info/pbr.json
tunir.egg-info/top_level.txt
tunirlib/__init__.py
tunirlib/config.py
tunirlib/testvm.py
tunirlib/tuniraws.py
tunirlib/tunirmultihost.py
tunirlib/tunirutils.py
tunirlib/tunirvagrant.py