Metadata-Version: 1.0
Name: tunir
Version: 0.17.3
Summary: Simple testing system.
Home-page: https://tunir.readthedocs.io
Author: Kushal Das
Author-email: kushaldas@gmail.com
License: GPLv2+
Platform: Linux
